BondGraphTools/__init__.py
BondGraphTools/actions.py
BondGraphTools/algebra.py
BondGraphTools/atomic.py
BondGraphTools/base.py
BondGraphTools/component_manager.py
BondGraphTools/compound.py
BondGraphTools/exceptions.py
BondGraphTools/fileio.py
BondGraphTools/port_hamiltonian.py
BondGraphTools/port_managers.py
BondGraphTools/reaction_builder.py
BondGraphTools/sim_tools.py
BondGraphTools/version.py
BondGraphTools/view.py
BondGraphTools/components/base.json
BondGraphTools/components/biochemical.json
BondGraphTools/components/electrical.json
BondGraphTools-0.4.6.dist-info/LICENSE
BondGraphTools-0.4.6.dist-info/METADATA
BondGraphTools-0.4.6.dist-info/WHEEL
BondGraphTools-0.4.6.dist-info/top_level.txt
BondGraphTools-0.4.6.dist-info/RECORD
