Metadata-Version: 2.1
Name: BondGraphTools
Version: 0.4.6
Summary: Bond Graph Modelling Toolkit
Home-page: https://github.com/BondGraphTools/BondGraphTools
Author: Pete Cudmore
Author-email: peter.cudmore@uqconnect.edu.au
License: UNKNOWN
Keywords: modelling control engineering
Platform: UNKNOWN
Classifier: Intended Audience :: Science/Research
Classifier: Intended Audience :: End Users/Desktop
Classifier: Development Status :: 3 - Alpha
Classifier: Programming Language :: Python :: 3.6
Classifier: Programming Language :: Python :: 3.7
Classifier: Programming Language :: Python :: 3.8
Classifier: Programming Language :: Python :: 3.9
Classifier: Topic :: Scientific/Engineering :: Mathematics
Classifier: Topic :: Scientific/Engineering
Classifier: License :: OSI Approved :: Apache Software License
Classifier: Operating System :: OS Independent
License-File: LICENSE
Requires-Dist: numpy
Requires-Dist: sympy
Requires-Dist: scipy
Requires-Dist: matplotlib
Requires-Dist: networkx
Requires-Dist: pyYAML
Requires-Dist: ordered-set
Provides-Extra: docs
Requires-Dist: sphinx (>=1.7) ; extra == 'docs'
Requires-Dist: sphinx-rtd-theme ; extra == 'docs'
